{"_ts":[1547527120,1547527588],"_r":{"breakdown":{"html":{"bytes":[2102,1658],"requests":[2,2]},"js":{"bytes":[18651,18651],"requests":[2,2]},"css":{"bytes":[334217,334236],"requests":[4,4]},"image":{"bytes":[105125,105094],"requests":[5,5]},"flash":{"bytes":[0,0],"requests":[0,0]},"font":{"bytes":[0,0],"requests":[0,0]},"video":{"bytes":[0,0],"requests":[0,0]},"other":{"bytes":[0,0],"requests":[1,0]}},"date":[1547527120,1547527588],"domElements":[69,69],"domInteractive":[636,282],"firstPaint":[786.9999999966,472.4999999999],"fullyLoaded":[1753,1397],"id":["190115_EM_bc53be9dd0742a5406f4823df0d7ef9b","190115_TY_a84ece93878f92d818884ae2b90bd651"],"loadTime":[1197,1200],"render":[800,500],"SpeedIndex":[1000,507],"TTFB":[503,180],"videoFrames":[[{"_i":"ms_000000.jpg","_t":0,"_vc":0},{"_i":"ms_000800.jpg","_t":800,"_vc":7},{"_i":"ms_000900.jpg","_t":900,"_vc":31},{"_i":"ms_001000.jpg","_t":1000,"_vc":77},{"_i":"ms_001100.jpg","_t":1100,"_vc":99},{"_i":"ms_001500.jpg","_t":1500,"_vc":99},{"_i":"ms_001600.jpg","_t":1600,"_vc":99},{"_i":"ms_001700.jpg","_t":1700,"_vc":99},{"_i":"ms_001800.jpg","_t":1800,"_vc":92},{"_i":"ms_001900.jpg","_t":1900,"_vc":100}],[{"_i":"ms_000000.jpg","_t":0,"_vc":0},{"_i":"ms_000500.jpg","_t":500,"_vc":99},{"_i":"ms_000700.jpg","_t":700,"_vc":99},{"_i":"ms_001200.jpg","_t":1200,"_vc":100}]],"visualComplete":[1900,1200],"lighthouse":[57,57],"pagespeed":[null,97]}}