{"_ts":[1551687061],"_r":{"breakdown":{"html":{"bytes":[2107],"requests":[2]},"js":{"bytes":[18790],"requests":[2]},"css":{"bytes":[334236],"requests":[4]},"image":{"bytes":[103850],"requests":[4]},"flash":{"bytes":[0],"requests":[0]},"font":{"bytes":[0],"requests":[0]},"video":{"bytes":[0],"requests":[0]},"other":{"bytes":[0],"requests":[1]}},"date":[1551687061],"domElements":[69],"domInteractive":[440],"firstPaint":[675.4350000047],"fullyLoaded":[1358],"id":["190304_6Q_3110155a68f7ee511b9bb189f5b692fa"],"loadTime":[1235],"render":[700],"SpeedIndex":[715],"TTFB":[331],"videoFrames":[[{"_i":"ms_000000.jpg","_t":0,"_vc":0},{"_i":"ms_000700.jpg","_t":700,"_vc":99},{"_i":"ms_001000.jpg","_t":1000,"_vc":99},{"_i":"ms_001100.jpg","_t":1100,"_vc":99},{"_i":"ms_001200.jpg","_t":1200,"_vc":99},{"_i":"ms_001400.jpg","_t":1400,"_vc":92},{"_i":"ms_001500.jpg","_t":1500,"_vc":100}]],"visualComplete":[1500],"lighthouse":[57],"pagespeed":[97]}}